monetize/__init__.py
monetize-1.0.0.dist-info/LICENSE
monetize-1.0.0.dist-info/METADATA
monetize-1.0.0.dist-info/WHEEL
monetize-1.0.0.dist-info/top_level.txt
monetize-1.0.0.dist-info/RECORD
