Metadata-Version: 2.1
Name: monetize
Version: 1.0.0
Summary: A python library to make some money
Author-email: Dylan Lang <hello@galway.group>
Maintainer-email: Dylan Lang <hello@galway.group>
License: MIT License
Project-URL: Homepage, https://github.com/dyvision/monetize
Project-URL: Documentation, https://github.com/dyvision/monetize?tab=readme-ov-file
Project-URL: Repository, https://github.com/dyvision/monetize.git
Keywords: Stripe,monetize,money,charge,finance,fintech
Classifier: Intended Audience :: Developers
Classifier: Topic :: Software Development :: Build Tools
Classifier: Development Status :: 5 - Production/Stable
Classifier: Programming Language :: Python
Requires-Python: >=3.8
License-File: LICENSE
Requires-Dist: requests
Requires-Dist: datetime
